llama_index/readers/mangoapps_guides/__init__.py
llama_index/readers/mangoapps_guides/base.py
llama_index_readers_mangoapps_guides-0.4.1.dist-info/METADATA
llama_index_readers_mangoapps_guides-0.4.1.dist-info/WHEEL
llama_index_readers_mangoapps_guides-0.4.1.dist-info/licenses/LICENSE
llama_index_readers_mangoapps_guides-0.4.1.dist-info/RECORD
