Metadata-Version: 2.4
Name: llama-index-readers-mangoapps-guides
Version: 0.4.1
Summary: llama-index readers mangoapps_guides integration
Author-email: Your Name <you@example.com>
Maintainer: mangoapps
License-Expression: MIT
License-File: LICENSE
Keywords: mangoapps
Requires-Python: <4.0,>=3.9
Requires-Dist: beautifulsoup4>=4.11.1
Requires-Dist: llama-index-core<0.15,>=0.13.0
Requires-Dist: requests>=2.28.1
